{"P244":[{"id":"Q15429542$BC630F8A-ED36-473B-B057-DB8903DBEAA7","rank":"normal","qualifiers":[],"references":[{"hash":"fa278ebfc458360e5aed63d5058cca83c46134f1","parts":[{"property":{"id":"P143","data-type":"wikibase-item"},"value":{"type":"value","content":"Q328"}}]}],"property":{"id":"P244","data-type":"external-id"},"value":{"type":"value","content":"n50003528"}}],"P31":[{"id":"Q15429542$8BB7300F-FEE6-4D76-97A2-2B94D6DC4909","rank":"normal","qualifiers":[],"references":[],"property":{"id":"P31","data-type":"wikibase-item"},"value":{"type":"value","content":"Q5"}}],"P21":[{"id":"Q15429542$8DE168BA-B9BA-4900-8017-EE71C0CCB4EC","rank":"normal","qualifiers":[],"references":[],"property":{"id":"P21","data-type":"wikibase-item"},"value":{"type":"value","content":"Q6581097"}}],"P106":[{"id":"Q15429542$A5B76DF8-A95F-4C41-84F0-F944E672D377","rank":"normal","qualifiers":[],"references":[{"hash":"617813ca5b3aecaf4710979655870fec6d538542","parts":[{"property":{"id":"P248","data-type":"wikibase-item"},"value":{"type":"value","content":"Q17166797"}}]}],"property":{"id":"P106","data-type":"wikibase-item"},"value":{"type":"value","content":"Q1792450"}}],"P735":[{"id":"Q15429542$0C44CF09-BDFE-4CE9-8AB9-F57F7433BBC8","rank":"normal","qualifiers":[],"references":[],"property":{"id":"P735","data-type":"wikibase-item"},"value":{"type":"value","content":"Q4925477"}}],"P69":[{"id":"Q15429542$6452EDA7-0E6D-4DE9-A948-55ECA24986A2","rank":"normal","qualifiers":[],"references":[],"property":{"id":"P69","data-type":"wikibase-item"},"value":{"type":"value","content":"Q332342"}}],"P570":[{"id":"Q15429542$3207D812-1DBE-4D98-AB2C-00E96FC75533","rank":"normal","qualifiers":[],"references":[{"hash":"fa278ebfc458360e5aed63d5058cca83c46134f1","parts":[{"property":{"id":"P143","data-type":"wikibase-item"},"value":{"type":"value","content":"Q328"}}]},{"hash":"1ebf4c776f2674bb914334d4ce57b09ffae00bc3","parts":[{"property":{"id":"P248","data-type":"wikibase-item"},"value":{"type":"value","content":"Q11148"}},{"property":{"id":"P854","data-type":"url"},"value":{"type":"value","content":"https:\/\/www.theguardian.com\/news\/2001\/jun\/19\/guardianobituaries.arts"}}]}],"property":{"id":"P570","data-type":"time"},"value":{"type":"value","content":{"time":"+2001-05-29T00:00:00Z","precision":11,"calendarmodel":"http:\/\/www.wikidata.org\/entity\/Q1985727"}}}],"P2332":[{"id":"Q15429542$2E49C88A-D8BF-4253-9BDD-8396235C9262","rank":"normal","qualifiers":[],"references":[],"property":{"id":"P2332","data-type":"external-id"},"value":{"type":"value","content":"flemingj"}}],"P569":[{"id":"Q15429542$6BF5BC1C-A256-4B48-B26B-E36E7D2DFF23","rank":"normal","qualifiers":[],"references":[],"property":{"id":"P569","data-type":"time"},"value":{"type":"value","content":{"time":"+1919-00-00T00:00:00Z","precision":9,"calendarmodel":"http:\/\/www.wikidata.org\/entity\/Q1985727"}}}],"P27":[{"id":"Q15429542$acc1680e-41fa-f692-c334-18ff9ae4fcfb","rank":"normal","qualifiers":[],"references":[],"property":{"id":"P27","data-type":"wikibase-item"},"value":{"type":"value","content":"Q145"}},{"id":"Q15429542$8820F42D-2AC9-4A2D-8996-AB10E6E22D76","rank":"normal","qualifiers":[],"references":[],"property":{"id":"P27","data-type":"wikibase-item"},"value":{"type":"value","content":"Q174193"}}],"P19":[{"id":"Q15429542$622644f7-4b7f-8941-8a6c-89f087496704","rank":"normal","qualifiers":[],"references":[],"property":{"id":"P19","data-type":"wikibase-item"},"value":{"type":"value","content":"Q504678"}}],"P20":[{"id":"Q15429542$d6b59248-4e6a-11c0-f490-42d5d6c8c2aa","rank":"normal","qualifiers":[],"references":[],"property":{"id":"P20","data-type":"wikibase-item"},"value":{"type":"value","content":"Q13373"}}],"P1343":[{"id":"Q15429542$566e88f9-44fc-dd17-dd5e-4c864ee1f934","rank":"normal","qualifiers":[{"property":{"id":"P1476","data-type":"monolingualtext"},"value":{"type":"value","content":{"text":"Fleming, John","language":"en"}}},{"property":{"id":"P854","data-type":"url"},"value":{"type":"value","content":"https:\/\/dictionaryofarthistorians.org\/flemingj.htm"}}],"references":[{"hash":"75086699ca294f096d545832b47b0ca2f5a9aacf","parts":[{"property":{"id":"P854","data-type":"url"},"value":{"type":"value","content":"https:\/\/dictionaryofarthistorians.org\/flemingj.htm"}},{"property":{"id":"P813","data-type":"time"},"value":{"type":"value","content":{"time":"+2016-02-03T00:00:00Z","precision":11,"calendarmodel":"http:\/\/www.wikidata.org\/entity\/Q1985727"}}}]}],"property":{"id":"P1343","data-type":"wikibase-item"},"value":{"type":"value","content":"Q17166797"}}],"P949":[{"id":"Q15429542$F5F7BC56-1573-4EF4-8B7B-D9607736D1C8","rank":"normal","qualifiers":[],"references":[],"property":{"id":"P949","data-type":"external-id"},"value":{"type":"value","content":"000198232"}}],"P214":[{"id":"Q15429542$60A3E681-200F-4A0B-9B03-F5BA0F5389F9","rank":"normal","qualifiers":[],"references":[{"hash":"06f547f7e98ae47d14e3172edb923b84726575b0","parts":[{"property":{"id":"P813","data-type":"time"},"value":{"type":"value","content":{"time":"+2017-11-01T00:00:00Z","precision":11,"calendarmodel":"http:\/\/www.wikidata.org\/entity\/Q1985727"}}},{"property":{"id":"P248","data-type":"wikibase-item"},"value":{"type":"value","content":"Q54919"}}]}],"property":{"id":"P214","data-type":"external-id"},"value":{"type":"value","content":"98341426"}}],"P227":[{"id":"Q15429542$DD6186BB-8B58-4D67-8A90-1E8A287C9DA6","rank":"normal","qualifiers":[],"references":[{"hash":"b3434801c6161374150a2eac89cbda0541890b74","parts":[{"property":{"id":"P214","data-type":"external-id"},"value":{"type":"value","content":"98341426"}},{"property":{"id":"P813","data-type":"time"},"value":{"type":"value","content":{"time":"+2017-11-01T00:00:00Z","precision":11,"calendarmodel":"http:\/\/www.wikidata.org\/entity\/Q1985727"}}},{"property":{"id":"P248","data-type":"wikibase-item"},"value":{"type":"value","content":"Q54919"}}]}],"property":{"id":"P227","data-type":"external-id"},"value":{"type":"value","content":"124232477"}}],"P268":[{"id":"Q15429542$11B7AC8B-15DD-45F9-9C6B-B08CDDEE9416","rank":"normal","qualifiers":[],"references":[{"hash":"b3434801c6161374150a2eac89cbda0541890b74","parts":[{"property":{"id":"P214","data-type":"external-id"},"value":{"type":"value","content":"98341426"}},{"property":{"id":"P813","data-type":"time"},"value":{"type":"value","content":{"time":"+2017-11-01T00:00:00Z","precision":11,"calendarmodel":"http:\/\/www.wikidata.org\/entity\/Q1985727"}}},{"property":{"id":"P248","data-type":"wikibase-item"},"value":{"type":"value","content":"Q54919"}}]}],"property":{"id":"P268","data-type":"external-id"},"value":{"type":"value","content":"12018516b"}}],"P269":[{"id":"Q15429542$58096954-0664-4EC8-9C94-AB40346E02FB","rank":"normal","qualifiers":[],"references":[{"hash":"b3434801c6161374150a2eac89cbda0541890b74","parts":[{"property":{"id":"P214","data-type":"external-id"},"value":{"type":"value","content":"98341426"}},{"property":{"id":"P813","data-type":"time"},"value":{"type":"value","content":{"time":"+2017-11-01T00:00:00Z","precision":11,"calendarmodel":"http:\/\/www.wikidata.org\/entity\/Q1985727"}}},{"property":{"id":"P248","data-type":"wikibase-item"},"value":{"type":"value","content":"Q54919"}}]}],"property":{"id":"P269","data-type":"external-id"},"value":{"type":"value","content":"028326563"}}],"P1015":[{"id":"Q15429542$1753ADE0-B01F-400A-8CB2-E7F5A6989493","rank":"normal","qualifiers":[],"references":[{"hash":"b3434801c6161374150a2eac89cbda0541890b74","parts":[{"property":{"id":"P214","data-type":"external-id"},"value":{"type":"value","content":"98341426"}},{"property":{"id":"P813","data-type":"time"},"value":{"type":"value","content":{"time":"+2017-11-01T00:00:00Z","precision":11,"calendarmodel":"http:\/\/www.wikidata.org\/entity\/Q1985727"}}},{"property":{"id":"P248","data-type":"wikibase-item"},"value":{"type":"value","content":"Q54919"}}]}],"property":{"id":"P1015","data-type":"external-id"},"value":{"type":"value","content":"2121096"}}],"P1207":[{"id":"Q15429542$7A3E5905-AD46-4694-B48D-6FA74F60537F","rank":"normal","qualifiers":[],"references":[{"hash":"b3434801c6161374150a2eac89cbda0541890b74","parts":[{"property":{"id":"P214","data-type":"external-id"},"value":{"type":"value","content":"98341426"}},{"property":{"id":"P813","data-type":"time"},"value":{"type":"value","content":{"time":"+2017-11-01T00:00:00Z","precision":11,"calendarmodel":"http:\/\/www.wikidata.org\/entity\/Q1985727"}}},{"property":{"id":"P248","data-type":"wikibase-item"},"value":{"type":"value","content":"Q54919"}}]}],"property":{"id":"P1207","data-type":"external-id"},"value":{"type":"value","content":"n93115139"}}],"P1273":[{"id":"Q15429542$DBECC485-C598-4500-94FE-F21E0A46B402","rank":"normal","qualifiers":[],"references":[{"hash":"b3434801c6161374150a2eac89cbda0541890b74","parts":[{"property":{"id":"P214","data-type":"external-id"},"value":{"type":"value","content":"98341426"}},{"property":{"id":"P813","data-type":"time"},"value":{"type":"value","content":{"time":"+2017-11-01T00:00:00Z","precision":11,"calendarmodel":"http:\/\/www.wikidata.org\/entity\/Q1985727"}}},{"property":{"id":"P248","data-type":"wikibase-item"},"value":{"type":"value","content":"Q54919"}}]}],"property":{"id":"P1273","data-type":"external-id"},"value":{"type":"value","content":"a10085403"}}],"P213":[{"id":"Q15429542$89224E79-37D0-42FA-BE13-9F099FB21100","rank":"normal","qualifiers":[],"references":[{"hash":"25bdbb7187c7cf1c689dccbfb4582904d96522a2","parts":[{"property":{"id":"P248","data-type":"wikibase-item"},"value":{"type":"value","content":"Q15222191"}},{"property":{"id":"P268","data-type":"external-id"},"value":{"type":"value","content":"12018516b"}},{"property":{"id":"P813","data-type":"time"},"value":{"type":"value","content":{"time":"+2017-11-22T00:00:00Z","precision":11,"calendarmodel":"http:\/\/www.wikidata.org\/entity\/Q1985727"}}}]}],"property":{"id":"P213","data-type":"external-id"},"value":{"type":"value","content":"0000 0001 0928 313X"}}],"P1368":[{"id":"Q15429542$6E4FBB44-8DC3-46B2-97F4-530F12F24267","rank":"normal","qualifiers":[],"references":[{"hash":"4d07dfd834825e346f0fb6fa4ae0d26f66a755a7","parts":[{"property":{"id":"P214","data-type":"external-id"},"value":{"type":"value","content":"98341426"}},{"property":{"id":"P813","data-type":"time"},"value":{"type":"value","content":{"time":"+2018-01-22T00:00:00Z","precision":11,"calendarmodel":"http:\/\/www.wikidata.org\/entity\/Q1985727"}}},{"property":{"id":"P248","data-type":"wikibase-item"},"value":{"type":"value","content":"Q54919"}}]}],"property":{"id":"P1368","data-type":"external-id"},"value":{"type":"value","content":"000039796"}}],"P1005":[{"id":"Q15429542$CF546C8F-627E-4651-99D4-06A85C097F7D","rank":"normal","qualifiers":[],"references":[],"property":{"id":"P1005","data-type":"external-id"},"value":{"type":"value","content":"245931"}}],"P1280":[{"id":"Q15429542$B510414D-74E9-4664-9599-AF18DA1C6CC0","rank":"normal","qualifiers":[],"references":[],"property":{"id":"P1280","data-type":"external-id"},"value":{"type":"value","content":"55037027"}}],"P1006":[{"id":"Q15429542$BEF64497-BB37-47D0-8839-387E45DD7ACD","rank":"normal","qualifiers":[],"references":[{"hash":"f9e47c29fdeb35080ae38cf8343f40bae422c09c","parts":[{"property":{"id":"P248","data-type":"wikibase-item"},"value":{"type":"value","content":"Q54919"}},{"property":{"id":"P813","data-type":"time"},"value":{"type":"value","content":{"time":"+2018-04-07T00:00:00Z","precision":11,"calendarmodel":"http:\/\/www.wikidata.org\/entity\/Q1985727"}}},{"property":{"id":"P214","data-type":"external-id"},"value":{"type":"value","content":"98341426"}}]}],"property":{"id":"P1006","data-type":"external-id"},"value":{"type":"value","content":"072170476"}}],"P5508":[{"id":"Q15429542$08B67A8D-8132-4EA7-9CA0-2A5D2FFDB51B","rank":"normal","qualifiers":[],"references":[{"hash":"cf9cd8e77c65d859e81f47d1dd7d536e85cbe98b","parts":[{"property":{"id":"P854","data-type":"url"},"value":{"type":"value","content":"https:\/\/www.archinform.net\/service\/wd_aiarch.php"}},{"property":{"id":"P813","data-type":"time"},"value":{"type":"value","content":{"time":"+2018-07-24T00:00:00Z","precision":11,"calendarmodel":"http:\/\/www.wikidata.org\/entity\/Q1985727"}}}]}],"property":{"id":"P5508","data-type":"external-id"},"value":{"type":"value","content":"4577"}}],"P2163":[{"id":"Q15429542$DA657E8D-CC28-4D30-88DF-69F00A4FEC27","rank":"normal","qualifiers":[],"references":[],"property":{"id":"P2163","data-type":"external-id"},"value":{"type":"value","content":"1729055"}}],"P734":[{"id":"Q15429542$2C80CF6A-A03F-4F4E-BB6E-30260F6F555E","rank":"normal","qualifiers":[],"references":[],"property":{"id":"P734","data-type":"wikibase-item"},"value":{"type":"value","content":"Q1427982"}}],"P950":[{"id":"Q15429542$6BDEA687-D5F1-4309-9DEF-79D9D70D53B5","rank":"normal","qualifiers":[],"references":[],"property":{"id":"P950","data-type":"external-id"},"value":{"type":"value","content":"XX885004"}}],"P691":[{"id":"Q15429542$F2927F0F-D1A2-49F5-A711-EEBEF0E0BF8F","rank":"normal","qualifiers":[],"references":[{"hash":"428de24a145417108b772ab4fe5e7f91ae0dd677","parts":[{"property":{"id":"P214","data-type":"external-id"},"value":{"type":"value","content":"98341426"}},{"property":{"id":"P248","data-type":"wikibase-item"},"value":{"type":"value","content":"Q54919"}},{"property":{"id":"P813","data-type":"time"},"value":{"type":"value","content":{"time":"+2018-12-16T00:00:00Z","precision":11,"calendarmodel":"http:\/\/www.wikidata.org\/entity\/Q1985727"}}}]}],"property":{"id":"P691","data-type":"external-id"},"value":{"type":"value","content":"jn19990002320"}}],"P7859":[{"id":"Q15429542$4B0DA521-EC32-467D-837D-8385E8E52DCB","rank":"normal","qualifiers":[],"references":[{"hash":"a6c723b06153ea18e19092f2efb731ab52edbec9","parts":[{"property":{"id":"P214","data-type":"external-id"},"value":{"type":"value","content":"98341426"}}]}],"property":{"id":"P7859","data-type":"external-id"},"value":{"type":"value","content":"lccn-n50003528"}}],"P1580":[{"id":"Q15429542$FD4D9491-71E5-4D1F-9DE6-E3C5D492AF8A","rank":"normal","qualifiers":[],"references":[{"hash":"de6da20b0989d3e0c911cb30f640b0fb0fa1f0dd","parts":[{"property":{"id":"P248","data-type":"wikibase-item"},"value":{"type":"value","content":"Q89570027"}},{"property":{"id":"P813","data-type":"time"},"value":{"type":"value","content":{"time":"+2020-04-01T00:00:00Z","precision":11,"calendarmodel":"http:\/\/www.wikidata.org\/entity\/Q1985727"}}}]}],"property":{"id":"P1580","data-type":"external-id"},"value":{"type":"value","content":"a1002456"}}],"P451":[{"id":"Q15429542$1607f71d-423b-f017-9774-88155e83339b","rank":"normal","qualifiers":[],"references":[{"hash":"9082a0d848e13c83447d7cdfaa2734723e2b516c","parts":[{"property":{"id":"P854","data-type":"url"},"value":{"type":"value","content":"https:\/\/www.theguardian.com\/artanddesign\/2016\/may\/26\/hugh-honour-obituary"}}]}],"property":{"id":"P451","data-type":"wikibase-item"},"value":{"type":"value","content":"Q3787443"}}],"P8750":[{"id":"Q15429542$2DE74701-EDC8-41FE-BAB4-7171D02A9C2F","rank":"normal","qualifiers":[],"references":[],"property":{"id":"P8750","data-type":"external-id"},"value":{"type":"value","content":"174735"}},{"id":"Q15429542$900E1838-7755-41BC-A509-10346530306E","rank":"normal","qualifiers":[],"references":[],"property":{"id":"P8750","data-type":"external-id"},"value":{"type":"value","content":"281427"}},{"id":"Q15429542$685D3B31-419F-4061-816A-96C8ABC226BC","rank":"normal","qualifiers":[],"references":[],"property":{"id":"P8750","data-type":"external-id"},"value":{"type":"value","content":"315314"}}],"P8851":[{"id":"Q15429542$3CD24CE5-2761-403D-8E84-C5A0FD53DA7D","rank":"normal","qualifiers":[],"references":[],"property":{"id":"P8851","data-type":"external-id"},"value":{"type":"value","content":"22655079"}}],"P646":[{"id":"Q15429542$B817E0D1-C1D0-41CC-9149-5A2C5B473489","rank":"normal","qualifiers":[],"references":[],"property":{"id":"P646","data-type":"external-id"},"value":{"type":"value","content":"\/m\/0xnbryk"}}],"P7293":[{"id":"Q15429542$5916B93D-5AAC-4E62-A51D-163B5F8DDB52","rank":"normal","qualifiers":[],"references":[],"property":{"id":"P7293","data-type":"external-id"},"value":{"type":"value","content":"9810605734905606"}}],"P9081":[{"id":"Q15429542$5AA88E94-7AB7-4981-A2C9-66851AB9827B","rank":"normal","qualifiers":[],"references":[],"property":{"id":"P9081","data-type":"external-id"},"value":{"type":"value","content":"44562"}}],"P9097":[{"id":"Q15429542$93C2D772-9B42-4D7D-AF77-48DCD50682E8","rank":"normal","qualifiers":[],"references":[],"property":{"id":"P9097","data-type":"external-id"},"value":{"type":"value","content":"12409234"}}],"P9164":[{"id":"Q15429542$EF61FABF-920F-4245-9C26-2968CF3484EA","rank":"normal","qualifiers":[],"references":[],"property":{"id":"P9164","data-type":"external-id"},"value":{"type":"value","content":"3062"}}],"P9251":[{"id":"Q15429542$3B5AE6E0-DA29-4A38-9207-E8BF2E36EDB7","rank":"normal","qualifiers":[],"references":[],"property":{"id":"P9251","data-type":"external-id"},"value":{"type":"value","content":"21675"}}],"P3987":[{"id":"Q15429542$BEFB5B36-ABF3-49E5-BA67-9AA86E45390E","rank":"normal","qualifiers":[],"references":[],"property":{"id":"P3987","data-type":"external-id"},"value":{"type":"value","content":"728893"}}],"P9322":[{"id":"Q15429542$D3980882-58C2-423D-9A26-8F1642209547","rank":"normal","qualifiers":[],"references":[{"hash":"68bd977df415052692b1d1f130b1bc8a05afa060","parts":[{"property":{"id":"P248","data-type":"wikibase-item"},"value":{"type":"value","content":"Q105821202"}},{"property":{"id":"P9322","data-type":"external-id"},"value":{"type":"value","content":"p0008791-Fleming-John-19192001"}},{"property":{"id":"P854","data-type":"url"},"value":{"type":"value","content":"https:\/\/ipac.svkkl.cz\/arl-kl\/cs\/detail-kl_us_auth-p0008791-Fleming-John-19192001"}},{"property":{"id":"P813","data-type":"time"},"value":{"type":"value","content":{"time":"+2021-03-22T00:00:00Z","precision":11,"calendarmodel":"http:\/\/www.wikidata.org\/entity\/Q1985727"}}}]}],"property":{"id":"P9322","data-type":"external-id"},"value":{"type":"value","content":"p0008791-Fleming-John-19192001"}}],"P1412":[{"id":"Q15429542$B6138952-4759-42BA-88D0-71405443A465","rank":"normal","qualifiers":[],"references":[],"property":{"id":"P1412","data-type":"wikibase-item"},"value":{"type":"value","content":"Q1860"}}],"P9984":[{"id":"Q15429542$B7F04F41-5B56-4892-95F1-4CF6582437D0","rank":"normal","qualifiers":[],"references":[],"property":{"id":"P9984","data-type":"external-id"},"value":{"type":"value","content":"981058512679606706"}}],"P8189":[{"id":"Q15429542$459BE30C-0A59-47E6-BCB6-ECBF46C8A73A","rank":"normal","qualifiers":[],"references":[],"property":{"id":"P8189","data-type":"external-id"},"value":{"type":"value","content":"987007312892505171"}}],"P6715":[{"id":"Q15429542$62D0F067-98B1-4B9B-BB52-DB9C13097B9B","rank":"normal","qualifiers":[],"references":[],"property":{"id":"P6715","data-type":"external-id"},"value":{"type":"value","content":"90229"}}],"P8034":[{"id":"Q15429542$06A1E9E5-EBFE-4F42-919B-E698917F550E","rank":"normal","qualifiers":[],"references":[],"property":{"id":"P8034","data-type":"external-id"},"value":{"type":"value","content":"495\/101765"}}],"P3348":[{"id":"Q15429542$A3D919F7-D105-427B-B64F-7E69D867D630","rank":"normal","qualifiers":[],"references":[],"property":{"id":"P3348","data-type":"external-id"},"value":{"type":"value","content":"66271"}}],"P1315":[{"id":"Q15429542$AFCC2F48-E382-4BF5-99B5-F6068DBCF516","rank":"normal","qualifiers":[],"references":[],"property":{"id":"P1315","data-type":"external-id"},"value":{"type":"value","content":"823214"}}],"P396":[{"id":"Q15429542$71BB9C3A-D21A-4D6E-AFB1-4C2189D54B28","rank":"normal","qualifiers":[{"property":{"id":"P1810","data-type":"string"},"value":{"type":"value","content":"Fleming, John <1919-2001>"}}],"references":[],"property":{"id":"P396","data-type":"external-id"},"value":{"type":"value","content":"RAVV030184"}}],"P3368":[{"id":"Q15429542$BFBD763E-30AB-44E6-9E51-203C7666B782","rank":"normal","qualifiers":[],"references":[],"property":{"id":"P3368","data-type":"external-id"},"value":{"type":"value","content":"2219113"}}],"P11686":[{"id":"Q15429542$AE1F63E8-E939-4E96-9516-EAEAF7CEBC4B","rank":"normal","qualifiers":[],"references":[],"property":{"id":"P11686","data-type":"external-id"},"value":{"type":"value","content":"981058512679606706"}}],"P1415":[{"id":"Q15429542$6ED8DB21-299F-4AAC-8A88-BB1DE0D4C5F8","rank":"normal","qualifiers":[],"references":[],"property":{"id":"P1415","data-type":"external-id"},"value":{"type":"value","content":"75955"}}]}